j2cli3/__init__.py
j2cli3/cli.py
j2cli3/context.py
j2cli3/extras/__init__.py
j2cli3/extras/filters.py
j2cli3-0.0.8.post0.dist-info/DESCRIPTION.rst
j2cli3-0.0.8.post0.dist-info/METADATA
j2cli3-0.0.8.post0.dist-info/RECORD
j2cli3-0.0.8.post0.dist-info/WHEEL
j2cli3-0.0.8.post0.dist-info/entry_points.txt
j2cli3-0.0.8.post0.dist-info/metadata.json
j2cli3-0.0.8.post0.dist-info/top_level.txt
